{
  "pmcid": "PMC5580210",
  "title": "Erratum to: Whole metagenome profiles of particulates collected from the International Space Station",
  "authors": [
    "Nicholas A Be",
    "Aram Avila Herrera",
    "Jonathan E Allen",
    "Nitin Singh",
    "Aleksandra Checinska Sielaff",
    "Crystal Jaing",
    "Kasthuri Venkateswaran"
  ],
  "year": "2017",
  "journal": "Microbiome",
  "doi": "10.1186/s40168 017 0330 2",
  "sections": {
    "abstract": "",
    "methods": "",
    "results": "",
    "discussion": "",
    "conclusion": ""
  },
  "provenance": {
    "source_type": "html",
    "fetched_at": "2025 10 04T03:07:35.935978",
    "url": "https://www.ncbi.nlm.nih.gov/pmc/articles/PMC5580210/"
  }
}